ecs_deplojo/__init__.py
ecs_deplojo/cli.py
ecs_deplojo/connection.py
ecs_deplojo/deployment.py
ecs_deplojo/exceptions.py
ecs_deplojo/logger.py
ecs_deplojo/register.py
ecs_deplojo/task_definitions.py
ecs_deplojo/utils.py
ecs_deplojo-0.10.1.dist-info/LICENSE
ecs_deplojo-0.10.1.dist-info/METADATA
ecs_deplojo-0.10.1.dist-info/WHEEL
ecs_deplojo-0.10.1.dist-info/entry_points.txt
ecs_deplojo-0.10.1.dist-info/top_level.txt
ecs_deplojo-0.10.1.dist-info/RECORD
