Metadata-Version: 2.2
Name: ecs-deplojo
Version: 0.10.1
Summary: Deployment tool for Amazon ECS
Author-email: "Lab Digital B.V." <opensource@labdigital.nl>
License: MIT
Requires-Python: >=3.9
License-File: LICENSE
Requires-Dist: boto3>=1.36.2
Requires-Dist: click>=8.1.8
Requires-Dist: pyaml>=25.1.0
Requires-Dist: pytz>=2024.2
